[
    {
        "icon": "icon iconfont icon-1st-homepage",
        "index": "home",
        "title": "首页"
    },
    {
        "icon": "icon iconfont icon-1st-operation-management",
        "index": "2",
        "title": "运营管理",
        "subs": [
            {
                "icon": "icon iconfont icon-2nd-service-directory",
                "index": "serviceCatalog",
                "title": "服务目录"
            },
            {
                "icon": "icon iconfont icon-2nd-code-management",
                "index": "codeTable",
                "title": "码表管理"
            }
        ]
    },
    {
        "icon": "icon iconfont icon-1st-system-management",
        "index": "3",
        "title": "系统管理",
        "subs": [
            {
                "icon": "icon iconfont icon-2nd-user-management",
                "index": "userTable",
                "title": "用户管理"
            },
            {
                "icon": "icon iconfont icon-2nd-tenant-management",
                "index": "tenantTable",
                "title": "租户管理"
            }
        ]
    }
]
